README.md
setup.py
src/vdk/plugin/jobs_troubleshoot/jobs_troubleshoot_plugin.py
src/vdk/plugin/jobs_troubleshoot/troubleshoot_configuration.py
src/vdk/plugin/jobs_troubleshoot/api/troubleshoot_utility.py
src/vdk/plugin/jobs_troubleshoot/troubleshoot_utilities/healthcheck_server.py
src/vdk/plugin/jobs_troubleshoot/troubleshoot_utilities/thread_dump.py
src/vdk/plugin/jobs_troubleshoot/troubleshoot_utilities/utilities_registry.py
src/vdk_jobs_troubleshooting.egg-info/PKG-INFO
src/vdk_jobs_troubleshooting.egg-info/SOURCES.txt
src/vdk_jobs_troubleshooting.egg-info/dependency_links.txt
src/vdk_jobs_troubleshooting.egg-info/entry_points.txt
src/vdk_jobs_troubleshooting.egg-info/requires.txt
src/vdk_jobs_troubleshooting.egg-info/top_level.txt
tests/test_utilities_registry.py