Metadata-Version: 2.1
Name: vdk-jobs-troubleshooting
Version: 0.2.824443273
Summary: Versatile Data Kit SDK troubleshooting plugin to assist in troubleshooting deployed data jobs.
Home-page: https://github.com/vmware/versatile-data-kit
Classifier: Development Status :: 4 - Beta
Classifier: License :: OSI Approved :: Apache Software License
Classifier: Programming Language :: Python :: 3.7
Classifier: Programming Language :: Python :: 3.8
Classifier: Programming Language :: Python :: 3.9
Classifier: Programming Language :: Python :: 3.10
Classifier: Programming Language :: Python :: 3.11
